pinax_cli-1.1.4.dist-info/DESCRIPTION.rst
pinax_cli-1.1.4.dist-info/METADATA
pinax_cli-1.1.4.dist-info/RECORD
pinax_cli-1.1.4.dist-info/WHEEL
pinax_cli-1.1.4.dist-info/entry_points.txt
pinax_cli-1.1.4.dist-info/metadata.json
pinax_cli-1.1.4.dist-info/top_level.txt
pinaxcli/__init__.py
pinaxcli/cli.py
pinaxcli/utils.py
